autogenstudio/__init__.py
autogenstudio/cli.py
autogenstudio/version.py
autogenstudio/database/__init__.py
autogenstudio/database/db_manager.py
autogenstudio/database/schema_manager.py
autogenstudio/datamodel/__init__.py
autogenstudio/datamodel/db.py
autogenstudio/datamodel/types.py
autogenstudio/gallery/__init__.py
autogenstudio/gallery/builder.py
autogenstudio/gallery/tools/__init__.py
autogenstudio/gallery/tools/bing_search.py
autogenstudio/gallery/tools/calculator.py
autogenstudio/gallery/tools/fetch_webpage.py
autogenstudio/gallery/tools/generate_image.py
autogenstudio/gallery/tools/google_search.py
autogenstudio/teammanager/__init__.py
autogenstudio/teammanager/teammanager.py
autogenstudio/utils/__init__.py
autogenstudio/utils/utils.py
autogenstudio/validation/__init__.py
autogenstudio/validation/component_test_service.py
autogenstudio/validation/validation_service.py
autogenstudio/web/__init__.py
autogenstudio/web/app.py
autogenstudio/web/config.py
autogenstudio/web/deps.py
autogenstudio/web/initialization.py
autogenstudio/web/serve.py
autogenstudio/web/auth/__init__.py
autogenstudio/web/auth/authroutes.py
autogenstudio/web/auth/dependencies.py
autogenstudio/web/auth/exceptions.py
autogenstudio/web/auth/manager.py
autogenstudio/web/auth/middleware.py
autogenstudio/web/auth/models.py
autogenstudio/web/auth/providers.py
autogenstudio/web/auth/wsauth.py
autogenstudio/web/managers/__init__.py
autogenstudio/web/managers/connection.py
autogenstudio/web/routes/__init__.py
autogenstudio/web/routes/gallery.py
autogenstudio/web/routes/runs.py
autogenstudio/web/routes/sessions.py
autogenstudio/web/routes/settingsroute.py
autogenstudio/web/routes/teams.py
autogenstudio/web/routes/validation.py
autogenstudio/web/routes/ws.py
autogenstudio/web/ui/071a7a8b27165c0a3e069b9edab6a5a9f8f229cc-7b5e4b43ea7a5453c259.js
autogenstudio/web/ui/071a7a8b27165c0a3e069b9edab6a5a9f8f229cc-7b5e4b43ea7a5453c259.js.map
autogenstudio-0.4.2.dist-info/LICENSE-CODE
autogenstudio-0.4.2.dist-info/METADATA
autogenstudio-0.4.2.dist-info/WHEEL
autogenstudio-0.4.2.dist-info/entry_points.txt
autogenstudio-0.4.2.dist-info/top_level.txt
autogenstudio-0.4.2.dist-info/RECORD
