Metadata-Version: 2.2
Name: autogenstudio
Version: 0.4.2
Summary: AutoGen Studio
Author-email: AutoGen Team <autogen@microsoft.com>
License:     MIT License
Project-URL: Homepage, https://github.com/microsoft/autogen
Project-URL: Bug Tracker, https://github.com/microsoft/autogen/issues
Classifier: Programming Language :: Python :: 3
Classifier: License :: OSI Approved :: MIT License
Classifier: Operating System :: OS Independent
Requires-Python: >=3.9
License-File: LICENSE-CODE
Requires-Dist: pydantic
Requires-Dist: pydantic-settings
Requires-Dist: fastapi[standard]
Requires-Dist: typer
Requires-Dist: aiofiles
Requires-Dist: python-dotenv
Requires-Dist: websockets
Requires-Dist: sqlmodel
Requires-Dist: psycopg
Requires-Dist: alembic
Requires-Dist: loguru
Requires-Dist: pyyaml
Requires-Dist: html2text
Requires-Dist: autogen-core<0.5,>=0.4.9.2
Requires-Dist: autogen-agentchat<0.5,>=0.4.9.2
Requires-Dist: autogen-ext[azure,magentic-one,openai]<0.5,>=0.4.2
Requires-Dist: anthropic
Provides-Extra: web
Requires-Dist: fastapi; extra == "web"
Requires-Dist: uvicorn; extra == "web"
Provides-Extra: database
Requires-Dist: psycopg; extra == "database"
